DatapulseTest/dataPulse.v
module dataPulse(
    input wire clk,
    output reg pulse_out
);

    reg [7:0] data = 8'b01000110;  // fixed data
    reg [3:0] count = 0;           // enough to count 0 to 8

    //initial pulse_out = 1;         // Set pulse_out = 1 initially

    always @(posedge clk) begin
        if (count < 8) begin
            pulse_out <= data[count];  // Send out bits one by one
            count <= count + 1;
        end
        else begin
            pulse_out <= 1;  // After 8 bits, keep pulse high
        end
    end

endmodule

DatapulseTest/dataPulse_tb.v
`include "dataPulse.v"
`timescale 1ns/1ns

module dataPulse_tb;
    reg clk;
    wire pulse_out;

    // Instantiate the module under test (UUT)
    dataPulse uut (
        .clk(clk),
        .pulse_out(pulse_out)
    );
    
    // Clock generation: toggle every 5 time units (period = 10)
    initial begin
        clk = 0;
        forever #10 clk = ~clk;  // 50MHz clock if 1 time unit = 1ns
    end

    // Simulation control
    initial begin
        // Optionally dump waves if your simulator supports it
        $dumpfile("dataPulse_tb.vcd");
        $dumpvars(0, dataPulse_tb);

        // Let the simulation run for some time
        #2000; // Run simulation for 200 time units
        $finish;
    end
endmodule

DatapulseTest/dataPulse_tb.vcd
$date
	Mon Apr 28 14:14:59 2025
$end
$version
	Icarus Verilog
$end
$timescale
	1ns
$end
$scope module dataPulse_tb $end
$var wire 1 ! pulse_out $end
$var reg 1 " clk $end
$scope module uut $end
$var wire 1 " clk $end
$var reg 4 # count [3:0] $end
$var reg 8 $ data [7:0] $end
$var reg 1 ! pulse_out $end
$upscope $end
$upscope $end
$enddefinitions $end
$comment Show the parameter values. $end
$dumpall
$end
#0
$dumpvars
b1000110 $
b0 #
0"
1!
$end
#5
b1 #
0!
1"
#10
0"
#15
b10 #
1!
1"
#20
0"
#25
b11 #
1"
#30
0"
#35
b100 #
0!
1"
#40
0"
#45
b101 #
1"
#50
0"
#55
b110 #
1"
#60
0"
#65
b111 #
1!
1"
#70
0"
#75
b1000 #
0!
1"
#80
0"
#85
1!
1"
